{
  "nav_label": "Blog",
  "title": "Research Log",
  "subtitle": "Stories, experiments, and longer reflections from ongoing projects.",
  "kicker": "Lab notebook",
  "archive_label": "View all posts",
  "page_labels": {
    "back": "Back to site",
    "search": "Search posts...",
    "allTags": "All topics",
    "empty": "No posts published yet.",
    "darkToLight": "Switch to light mode",
    "lightToDark": "Switch to dark mode"
  },
  "post_labels": {
    "backBlog": "Back to blog",
    "backHome": "Home",
    "bottomBackBlog": "Back to blog index",
    "bottomBackHome": "Return to homepage",
    "darkToLight": "Switch to light mode",
    "lightToDark": "Switch to dark mode",
    "updated": "Updated",
    "reading": "read",
    "missing": "We could not find this article. Please check the URL or return to the blog index."
  },
  "blogs": [
    {
      "slug": "launching-the-research-blog",
      "title": "Why This Blog Exists",
      "summary": "Setting the tone for longer-form updates and how they complement the rest of the site.",
      "post_time": "2025-01-05 09:00",
      "author": "Joshua Xu",
      "tags": [
        "Meta",
        "Writing"
      ]
    },
    {
      "slug": "robotics-field-notes",
      "title": "Field Notes: Indoor Avoidance Trials",
      "summary": "Notes from week three inside the test arena, smoothing controllers and taming a moody GPU.",
      "post_time": "2025-01-12 14:30",
      "author": "Joshua Xu",
      "tags": [
        "Robotics",
        "Field Notes"
      ]
    }
  ]
}
